setup.py
im_man/__init__.py
im_man.egg-info/PKG-INFO
im_man.egg-info/SOURCES.txt
im_man.egg-info/dependency_links.txt
im_man.egg-info/not-zip-safe
im_man.egg-info/top_level.txt