Metadata-Version: 1.0
Name: im-man
Version: 0.1
Summary: used for some perpose
Home-page: UNKNOWN
Author: UNKNOWN
Author-email: UNKNOWN
License: UNKNOWN
Platform: UNKNOWN
